{"stats":{"minecraft:picked_up":{"minecraft:lime_wool":1,"minecraft:repeater":359,"minecraft:stone_button":1,"minecraft:redstone":4556,"minecraft:oak_sign":12,"minecraft:comparator":199,"minecraft:lever":152,"minecraft:polished_blackstone_button":20,"minecraft:redstone_torch":138},"minecraft:custom":{"minecraft:time_since_rest":1681066,"minecraft:sprint_one_cm":50942,"minecraft:walk_one_cm":636298,"minecraft:drop":4,"minecraft:damage_dealt":50,"minecraft:fly_one_cm":8419923,"minecraft:open_barrel":41,"minecraft:crouch_one_cm":22225,"minecraft:play_time":1681066,"minecraft:sneak_time":79136,"minecraft:walk_under_water_one_cm":32513,"minecraft:aviate_one_cm":50865,"minecraft:jump":1208,"minecraft:leave_game":35,"minecraft:walk_on_water_one_cm":4188,"minecraft:time_since_death":1681066,"minecraft:total_world_time":2630153},"minecraft:used":{"minecraft:redstone_torch":360,"minecraft:purple_stained_glass":337,"minecraft:glass":197,"minecraft:lever":255,"minecraft:water_bucket":1,"minecraft:black_wool":562,"minecraft:lava_bucket":3,"minecraft:firework_rocket":8,"minecraft:light_gray_stained_glass":70,"minecraft:red_wool":219,"minecraft:redstone":4546,"minecraft:elytra":1,"minecraft:lime_wool":130,"minecraft:stone_button":1,"minecraft:oak_sign":19,"minecraft:blue_wool":525,"minecraft:spruce_planks":150,"minecraft:sandstone":294,"minecraft:redstone_block":34,"minecraft:magenta_stained_glass":106,"minecraft:pink_wool":640,"minecraft:structure_block":90,"minecraft:barrel":19,"minecraft:yellow_wool":120,"minecraft:white_wool":111,"minecraft:light_gray_wool":1858,"minecraft:orange_stained_glass":63,"minecraft:birch_button":1,"minecraft:repeater":828,"minecraft:redstone_lamp":741,"minecraft:target":39,"minecraft:comparator":130,"minecraft:magenta_wool":571,"minecraft:blue_stained_glass":685,"minecraft:light_blue_wool":659,"minecraft:white_stained_glass":11,"minecraft:pink_stained_glass":21,"minecraft:orange_wool":369,"minecraft:polished_blackstone_button":43,"minecraft:stripped_oak_log":3,"minecraft:gray_wool":1688,"minecraft:oak_hanging_sign":5,"minecraft:observer":8,"minecraft:light_blue_stained_glass":88,"minecraft:purple_wool":269,"minecraft:gray_stained_glass":104},"minecraft:dropped":{"minecraft:lever":2,"minecraft:lime_wool":1,"minecraft:redstone":1}},"DataVersion":4082}